mlx_lm_lora/__init__.py
mlx_lm_lora/__main__.py
mlx_lm_lora/_version.py
mlx_lm_lora/py.typed
mlx_lm_lora/synthetic_dpo.py
mlx_lm_lora/synthetic_sft.py
mlx_lm_lora/train.py
mlx_lm_lora/train_judge.py
mlx_lm_lora/utils.py
mlx_lm_lora/trainer/__init__.py
mlx_lm_lora/trainer/cpo_trainer.py
mlx_lm_lora/trainer/datasets.py
mlx_lm_lora/trainer/dpo_trainer.py
mlx_lm_lora/trainer/grpo_reward_functions.py
mlx_lm_lora/trainer/grpo_trainer.py
mlx_lm_lora/trainer/judge.py
mlx_lm_lora/trainer/online_dpo_trainer.py
mlx_lm_lora/trainer/orpo_trainer.py
mlx_lm_lora/trainer/rflhf_trainer.py
mlx_lm_lora/trainer/sft_trainer.py
mlx_lm_lora/trainer/xpo_trainer.py
mlx_lm_lora-0.8.5.dist-info/licenses/LICENSE
mlx_lm_lora-0.8.5.dist-info/METADATA
mlx_lm_lora-0.8.5.dist-info/WHEEL
mlx_lm_lora-0.8.5.dist-info/entry_points.txt
mlx_lm_lora-0.8.5.dist-info/top_level.txt
mlx_lm_lora-0.8.5.dist-info/RECORD
